faktura/__init__.py
faktura/admin.py
faktura/apps.py
faktura/models.py
faktura/settings.py
faktura/urls.py
faktura/utils.py
faktura/views.py
faktura/management/commands/__init__.py
faktura/management/commands/clone_invoice.py
faktura/management/commands/generate_invoice_from_proforma.py
faktura/management/commands/__pycache__/__init__.cpython-37.pyc
faktura/management/commands/__pycache__/clone_invoice.cpython-37.pyc
faktura/management/commands/__pycache__/generate_invoice_from_proforma.cpython-37.pyc
faktura/migrations/0001_initial.py
faktura/migrations/__init__.py
faktura/migrations/__pycache__/0001_initial.cpython-37.pyc
faktura/migrations/__pycache__/__init__.cpython-37.pyc
faktura/templates/faktura/base.html
faktura/templates/faktura/invoice_archive_year.html
faktura/templates/faktura/invoice_detail.html
faktura/templates/faktura/invoice_list.html
faktura/templates/faktura/includes/invoices_list.html
faktura/templates/faktura/includes/pagination.html
faktura/tests/__init__.py
faktura/tests/test_models.py
django_faktura-0.1.dist-info/LICENSE
django_faktura-0.1.dist-info/METADATA
django_faktura-0.1.dist-info/WHEEL
django_faktura-0.1.dist-info/top_level.txt
django_faktura-0.1.dist-info/RECORD
